{
    "Agriculture_Ranking": [
        {
            "college_id": "IR-G-U-0101",
            "college_name": "Indian Agricultural Research Institute",
            "odd href": "https://www.nirfindia.org/nirfpdfcdn/2024/pdf/Agriculture/IR-G-U-0101.pdf",
            "odd href 2": "https://www.nirfindia.org/nirfpdfcdn/2024/graph/Agriculture/IR-G-U-0101.jpg",
            "TLR (100)": "89.80",
            "RPC (100)": "92.79",
            "GO (100)": "82.81",
            "OI (100)": "73.74",
            "PERCEPTION (100)": "92.71",
            "college_city": "New Delhi",
            "college_state": "Delhi",
            "ranking_score": "87.98",
            "college_rank": "1"
        },
        {
            "TLR (100)": "78.54",
            "RPC (100)": "60.44",
            "GO (100)": "87.07",
            "OI (100)": "62.65",
            "PERCEPTION (100)": "58.08",
            "ranking_score": "71.18",
            "college_id": "IR-G-U-0171",
            "college_name": "ICAR - National Dairy Research Institute",
            "even href": "https://www.nirfindia.org/nirfpdfcdn/2024/pdf/Agriculture/IR-G-U-0171.pdf",
            "even href 2": "https://www.nirfindia.org/nirfpdfcdn/2024/graph/Agriculture/IR-G-U-0171.jpg",
            "college_city": "Karnal",
            "college_state": "Haryana",
            "college_rank": "2"
        },
        {
            "college_id": "IR-G-U-0381",
            "college_name": "Punjab Agricultural University",
            "odd href": "https://www.nirfindia.org/nirfpdfcdn/2024/pdf/Agriculture/IR-G-U-0381.pdf",
            "odd href 2": "https://www.nirfindia.org/nirfpdfcdn/2024/graph/Agriculture/IR-G-U-0381.jpg",
            "TLR (100)": "87.98",
            "RPC (100)": "67.49",
            "GO (100)": "51.84",
            "OI (100)": "49.96",
            "PERCEPTION (100)": "76.16",
            "college_city": "Ludhiana",
            "college_state": "Punjab",
            "ranking_score": "69.63",
            "college_rank": "3"
        },
        {
            "TLR (100)": "67.94",
            "RPC (100)": "74.30",
            "GO (100)": "71.04",
            "OI (100)": "58.96",
            "PERCEPTION (100)": "55.38",
            "ranking_score": "68.32",
            "college_id": "IR-G-U-0500",
            "college_name": "Banaras Hindu University",
            "even href": "https://www.nirfindia.org/nirfpdfcdn/2024/pdf/Agriculture/IR-G-U-0500.pdf",
            "even href 2": "https://www.nirfindia.org/nirfpdfcdn/2024/graph/Agriculture/IR-G-U-0500.jpg",
            "college_city": "Varanasi",
            "college_state": "Uttar Pradesh",
            "college_rank": "4"
        },
        {
            "college_id": "IR-G-U-0518",
            "college_name": "Indian Veterinary Research Institute, Izatnagar",
            "odd href": "https://www.nirfindia.org/nirfpdfcdn/2024/pdf/Agriculture/IR-G-U-0518.pdf",
            "odd href 2": "https://www.nirfindia.org/nirfpdfcdn/2024/graph/Agriculture/IR-G-U-0518.jpg",
            "TLR (100)": "87.23",
            "RPC (100)": "54.71",
            "GO (100)": "77.21",
            "OI (100)": "56.30",
            "PERCEPTION (100)": "41.12",
            "college_city": "Bareilly",
            "college_state": "Uttar Pradesh",
            "ranking_score": "67.76",
            "college_rank": "5"
        },
        {
            "TLR (100)": "83.47",
            "RPC (100)": "42.55",
            "GO (100)": "58.01",
            "OI (100)": "55.06",
            "PERCEPTION (100)": "100.00",
            "ranking_score": "64.92",
            "college_id": "IR-G-U-0485",
            "college_name": "Tamil Nadu Agricultural University",
            "even href": "https://www.nirfindia.org/nirfpdfcdn/2024/pdf/Agriculture/IR-G-U-0485.pdf",
            "even href 2": "https://www.nirfindia.org/nirfpdfcdn/2024/graph/Agriculture/IR-G-U-0485.jpg",
            "college_city": "Coimbatore",
            "college_state": "Tamil Nadu",
            "college_rank": "6"
        },
        {
            "college_id": "IR-G-U-0159",
            "college_name": "Chaudhary Charan Singh Haryana Agricultural University",
            "odd href": "https://www.nirfindia.org/nirfpdfcdn/2024/pdf/Agriculture/IR-G-U-0159.pdf",
            "odd href 2": "https://www.nirfindia.org/nirfpdfcdn/2024/graph/Agriculture/IR-G-U-0159.jpg",
            "TLR (100)": "93.80",
            "RPC (100)": "35.16",
            "GO (100)": "66.87",
            "OI (100)": "50.24",
            "PERCEPTION (100)": "66.70",
            "college_city": "Hisar",
            "college_state": "Haryana",
            "ranking_score": "63.75",
            "college_rank": "7"
        },
        {
            "TLR (100)": "70.89",
            "RPC (100)": "43.52",
            "GO (100)": "76.23",
            "OI (100)": "51.20",
            "PERCEPTION (100)": "70.74",
            "ranking_score": "61.77",
            "college_id": "IR-G-U-0554",
            "college_name": "G.B. Pant Universtiy of Agriculture and Technology",
            "even href": "https://www.nirfindia.org/nirfpdfcdn/2024/pdf/Agriculture/IR-G-U-0554.pdf",
            "even href 2": "https://www.nirfindia.org/nirfpdfcdn/2024/graph/Agriculture/IR-G-U-0554.jpg",
            "college_city": "Pantnagar",
            "college_state": "Uttarakhand",
            "college_rank": "8"
        },
        {
            "college_id": "IR-G-U-0293",
            "college_name": "Central Institute of Fisheries Education, Fishries University",
            "odd href": "https://www.nirfindia.org/nirfpdfcdn/2024/pdf/Agriculture/IR-G-U-0293.pdf",
            "odd href 2": "https://www.nirfindia.org/nirfpdfcdn/2024/graph/Agriculture/IR-G-U-0293.jpg",
            "TLR (100)": "74.76",
            "RPC (100)": "42.17",
            "GO (100)": "82.18",
            "OI (100)": "75.00",
            "PERCEPTION (100)": "23.49",
            "college_city": "Mumbai",
            "college_state": "Maharashtra",
            "ranking_score": "61.37",
            "college_rank": "9"
        },
        {
            "TLR (100)": "77.79",
            "RPC (100)": "49.66",
            "GO (100)": "77.14",
            "OI (100)": "46.36",
            "PERCEPTION (100)": "27.30",
            "ranking_score": "61.04",
            "college_id": "IR-G-U-0200",
            "college_name": "Sher-e-Kashmir University of Agricultural Science and Technology of Kashmir",
            "even href": "https://www.nirfindia.org/nirfpdfcdn/2024/pdf/Agriculture/IR-G-U-0200.pdf",
            "even href 2": "https://www.nirfindia.org/nirfpdfcdn/2024/graph/Agriculture/IR-G-U-0200.jpg",
            "college_city": "Srinagar",
            "college_state": "Jammu and Kashmir",
            "college_rank": "10"
        },
        {
            "college_id": "IR-G-U-0248",
            "college_name": "University of Agricultural Sciences",
            "odd href": "https://www.nirfindia.org/nirfpdfcdn/2024/pdf/Agriculture/IR-G-U-0248.pdf",
            "odd href 2": "https://www.nirfindia.org/nirfpdfcdn/2024/graph/Agriculture/IR-G-U-0248.jpg",
            "TLR (100)": "84.43",
            "RPC (100)": "28.65",
            "GO (100)": "67.62",
            "OI (100)": "58.72",
            "PERCEPTION (100)": "58.08",
            "college_city": "Bengaluru",
            "college_state": "Karnataka",
            "ranking_score": "59.13",
            "college_rank": "11"
        },
        {
            "TLR (100)": "69.00",
            "RPC (100)": "49.03",
            "GO (100)": "54.68",
            "OI (100)": "57.26",
            "PERCEPTION (100)": "47.19",
            "ranking_score": "56.80",
            "college_id": "IR-G-C-45375",
            "college_name": "National Institute of Food Technology, Entrepreneurship and Management",
            "even href": "https://www.nirfindia.org/nirfpdfcdn/2024/pdf/Agriculture/IR-G-C-45375.pdf",
            "even href 2": "https://www.nirfindia.org/nirfpdfcdn/2024/graph/Agriculture/IR-G-C-45375.jpg",
            "college_city": "Thanjavur",
            "college_state": "Tamil Nadu",
            "college_rank": "12"
        },
        {
            "college_id": "IR-G-U-0568",
            "college_name": "Bidhan Chandra Krishi Vishwavidyalaya",
            "odd href": "https://www.nirfindia.org/nirfpdfcdn/2024/pdf/Agriculture/IR-G-U-0568.pdf",
            "odd href 2": "https://www.nirfindia.org/nirfpdfcdn/2024/graph/Agriculture/IR-G-U-0568.jpg",
            "TLR (100)": "76.17",
            "RPC (100)": "37.10",
            "GO (100)": "78.20",
            "OI (100)": "29.45",
            "PERCEPTION (100)": "41.12",
            "college_city": "Nadia",
            "college_state": "West Bengal",
            "ranking_score": "56.67",
            "college_rank": "13"
        },
        {
            "TLR (100)": "88.75",
            "RPC (100)": "20.14",
            "GO (100)": "62.59",
            "OI (100)": "56.58",
            "PERCEPTION (100)": "48.31",
            "ranking_score": "55.67",
            "college_id": "IR-G-U-0048",
            "college_name": "Assam Agricultural University",
            "even href": "https://www.nirfindia.org/nirfpdfcdn/2024/pdf/Agriculture/IR-G-U-0048.pdf",
            "even href 2": "https://www.nirfindia.org/nirfpdfcdn/2024/graph/Agriculture/IR-G-U-0048.jpg",
            "college_city": "Jorhat",
            "college_state": "Assam",
            "college_rank": "14"
        },
        {
            "college_id": "IR-G-U-0360",
            "college_name": "Odisha University of Agriculture and Technology",
            "odd href": "https://www.nirfindia.org/nirfpdfcdn/2024/pdf/Agriculture/IR-G-U-0360.pdf",
            "odd href 2": "https://www.nirfindia.org/nirfpdfcdn/2024/graph/Agriculture/IR-G-U-0360.jpg",
            "TLR (100)": "79.36",
            "RPC (100)": "27.12",
            "GO (100)": "69.90",
            "OI (100)": "56.10",
            "PERCEPTION (100)": "41.12",
            "college_city": "Khordha",
            "college_state": "Odisha",
            "ranking_score": "55.65",
            "college_rank": "15"
        },
        {
            "TLR (100)": "83.95",
            "RPC (100)": "27.77",
            "GO (100)": "57.50",
            "OI (100)": "47.40",
            "PERCEPTION (100)": "55.38",
            "ranking_score": "55.30",
            "college_id": "IR-G-U-0257",
            "college_name": "Kerala Agricultural University",
            "even href": "https://www.nirfindia.org/nirfpdfcdn/2024/pdf/Agriculture/IR-G-U-0257.pdf",
            "even href 2": "https://www.nirfindia.org/nirfpdfcdn/2024/graph/Agriculture/IR-G-U-0257.jpg",
            "college_city": "Thrissur",
            "college_state": "Kerala",
            "college_rank": "16"
        },
        {
            "college_id": "IR-G-U-0487",
            "college_name": "Tamil Nadu Veterinary and Animal Sciences University",
            "odd href": "https://www.nirfindia.org/nirfpdfcdn/2024/pdf/Agriculture/IR-G-U-0487.pdf",
            "odd href 2": "https://www.nirfindia.org/nirfpdfcdn/2024/graph/Agriculture/IR-G-U-0487.jpg",
            "TLR (100)": "78.36",
            "RPC (100)": "28.01",
            "GO (100)": "61.79",
            "OI (100)": "55.68",
            "PERCEPTION (100)": "53.48",
            "college_city": "Chennai",
            "college_state": "Tamil Nadu",
            "ranking_score": "55.19",
            "college_rank": "17"
        },
        {
            "TLR (100)": "75.60",
            "RPC (100)": "30.21",
            "GO (100)": "73.79",
            "OI (100)": "50.89",
            "PERCEPTION (100)": "30.79",
            "ranking_score": "54.67",
            "college_id": "IR-G-U-0181",
            "college_name": "Dr. Y.S. Parmar University of Horticulture and Forestry",
            "even href": "https://www.nirfindia.org/nirfpdfcdn/2024/pdf/Agriculture/IR-G-U-0181.pdf",
            "even href 2": "https://www.nirfindia.org/nirfpdfcdn/2024/graph/Agriculture/IR-G-U-0181.jpg",
            "college_city": "Solan",
            "college_state": "Himachal Pradesh",
            "college_rank": "18"
        },
        {
            "college_id": "IR-G-U-0179",
            "college_name": "Chaudhary Sarwan Kumar Himachal Pardesh Krishi Vishvavidyalaya",
            "odd href": "https://www.nirfindia.org/nirfpdfcdn/2024/pdf/Agriculture/IR-G-U-0179.pdf",
            "odd href 2": "https://www.nirfindia.org/nirfpdfcdn/2024/graph/Agriculture/IR-G-U-0179.jpg",
            "TLR (100)": "78.93",
            "RPC (100)": "28.03",
            "GO (100)": "71.95",
            "OI (100)": "48.31",
            "PERCEPTION (100)": "32.43",
            "college_city": "Kangra",
            "college_state": "Himachal Pradesh",
            "ranking_score": "54.55",
            "college_rank": "19"
        },
        {
            "TLR (100)": "76.00",
            "RPC (100)": "32.95",
            "GO (100)": "66.76",
            "OI (100)": "55.30",
            "PERCEPTION (100)": "23.49",
            "ranking_score": "53.91",
            "college_id": "IR-G-U-0199",
            "college_name": "Sher-e-Kashmir University of Agricultural Science and Technology of Jammu",
            "even href": "https://www.nirfindia.org/nirfpdfcdn/2024/pdf/Agriculture/IR-G-U-0199.pdf",
            "even href 2": "https://www.nirfindia.org/nirfpdfcdn/2024/graph/Agriculture/IR-G-U-0199.jpg",
            "college_city": "Jammu",
            "college_state": "Jammu and Kashmir",
            "college_rank": "20"
        },
        {
            "college_id": "IR-G-S-8898",
            "college_name": "National Institute of Food Technology, Enterprenurship and Management",
            "odd href": "https://www.nirfindia.org/nirfpdfcdn/2024/pdf/Agriculture/IR-G-S-8898.pdf",
            "odd href 2": "https://www.nirfindia.org/nirfpdfcdn/2024/graph/Agriculture/IR-G-S-8898.jpg",
            "TLR (100)": "53.92",
            "RPC (100)": "45.47",
            "GO (100)": "66.09",
            "OI (100)": "66.01",
            "PERCEPTION (100)": "27.30",
            "college_city": "Sonipat",
            "college_state": "Haryana",
            "ranking_score": "52.37",
            "college_rank": "21"
        },
        {
            "TLR (100)": "53.08",
            "RPC (100)": "53.13",
            "GO (100)": "49.77",
            "OI (100)": "72.72",
            "PERCEPTION (100)": "19.29",
            "ranking_score": "51.01",
            "college_id": "IR-G-U-0379",
            "college_name": "Lovely Professional University",
            "even href": "https://www.nirfindia.org/nirfpdfcdn/2024/pdf/Agriculture/IR-G-U-0379.pdf",
            "even href 2": "https://www.nirfindia.org/nirfpdfcdn/2024/graph/Agriculture/IR-G-U-0379.jpg",
            "college_city": "Phagwara",
            "college_state": "Punjab",
            "college_rank": "22"
        },
        {
            "college_id": "IR-G-U-0123",
            "college_name": "Anand Agricultural University",
            "odd href": "https://www.nirfindia.org/nirfpdfcdn/2024/pdf/Agriculture/IR-G-U-0123.pdf",
            "odd href 2": "https://www.nirfindia.org/nirfpdfcdn/2024/graph/Agriculture/IR-G-U-0123.jpg",
            "TLR (100)": "77.11",
            "RPC (100)": "16.90",
            "GO (100)": "73.32",
            "OI (100)": "41.31",
            "PERCEPTION (100)": "37.00",
            "college_city": "Anand",
            "college_state": "Gujarat",
            "ranking_score": "50.69",
            "college_rank": "23"
        },
        {
            "TLR (100)": "73.15",
            "RPC (100)": "13.74",
            "GO (100)": "75.64",
            "OI (100)": "53.48",
            "PERCEPTION (100)": "39.79",
            "ranking_score": "50.52",
            "college_id": "IR-G-U-0246",
            "college_name": "University of Agricultural Sciences",
            "even href": "https://www.nirfindia.org/nirfpdfcdn/2024/pdf/Agriculture/IR-G-U-0246.pdf",
            "even href 2": "https://www.nirfindia.org/nirfpdfcdn/2024/graph/Agriculture/IR-G-U-0246.jpg",
            "college_city": "Dharwad",
            "college_state": "Karnataka",
            "college_rank": "24"
        },
        {
            "college_id": "IR-G-U-0375",
            "college_name": "Guru Angad Dev Veterinary and Animal Sciences University",
            "odd href": "https://www.nirfindia.org/nirfpdfcdn/2024/pdf/Agriculture/IR-G-U-0375.pdf",
            "odd href 2": "https://www.nirfindia.org/nirfpdfcdn/2024/graph/Agriculture/IR-G-U-0375.jpg",
            "TLR (100)": "76.47",
            "RPC (100)": "34.20",
            "GO (100)": "48.40",
            "OI (100)": "45.61",
            "PERCEPTION (100)": "30.79",
            "college_city": "Ludhiana",
            "college_state": "Punjab",
            "ranking_score": "50.52",
            "college_rank": "24"
        },
        {
            "TLR (100)": "80.65",
            "RPC (100)": "14.45",
            "GO (100)": "61.73",
            "OI (100)": "53.89",
            "PERCEPTION (100)": "39.79",
            "ranking_score": "50.24",
            "college_id": "IR-G-U-0004",
            "college_name": "Acharya N G Ranga Agricultural University",
            "even href": "https://www.nirfindia.org/nirfpdfcdn/2024/pdf/Agriculture/IR-G-U-0004.pdf",
            "even href 2": "https://www.nirfindia.org/nirfpdfcdn/2024/graph/Agriculture/IR-G-U-0004.jpg",
            "college_city": "Guntur",
            "college_state": "Andhra Pradesh",
            "college_rank": "26"
        },
        {
            "college_id": "IR-G-U-0443",
            "college_name": "Annamalai University",
            "odd href": "https://www.nirfindia.org/nirfpdfcdn/2024/pdf/Agriculture/IR-G-U-0443.pdf",
            "odd href 2": "https://www.nirfindia.org/nirfpdfcdn/2024/graph/Agriculture/IR-G-U-0443.jpg",
            "TLR (100)": "64.34",
            "RPC (100)": "26.05",
            "GO (100)": "66.43",
            "OI (100)": "47.96",
            "PERCEPTION (100)": "47.19",
            "college_city": "Annamalainagar",
            "college_state": "Tamil Nadu",
            "ranking_score": "49.92",
            "college_rank": "27"
        },
        {
            "TLR (100)": "71.90",
            "RPC (100)": "22.66",
            "GO (100)": "73.21",
            "OI (100)": "15.91",
            "PERCEPTION (100)": "37.00",
            "ranking_score": "48.30",
            "college_id": "IR-G-U-0591",
            "college_name": "West Bengal University of Animal and Fishery Sciences",
            "even href": "https://www.nirfindia.org/nirfpdfcdn/2024/pdf/Agriculture/IR-G-U-0591.pdf",
            "even href 2": "https://www.nirfindia.org/nirfpdfcdn/2024/graph/Agriculture/IR-G-U-0591.jpg",
            "college_city": "Kolkata",
            "college_state": "West Bengal",
            "college_rank": "28"
        },
        {
            "college_id": "IR-G-U-0075",
            "college_name": "Dr Rajendra Prasad Central Agricultural University",
            "odd href": "https://www.nirfindia.org/nirfpdfcdn/2024/pdf/Agriculture/IR-G-U-0075.pdf",
            "odd href 2": "https://www.nirfindia.org/nirfpdfcdn/2024/graph/Agriculture/IR-G-U-0075.jpg",
            "TLR (100)": "74.79",
            "RPC (100)": "19.88",
            "GO (100)": "58.79",
            "OI (100)": "60.83",
            "PERCEPTION (100)": "17.03",
            "college_city": "Samastipur",
            "college_state": "Bihar",
            "ranking_score": "47.94",
            "college_rank": "29"
        },
        {
            "TLR (100)": "61.71",
            "RPC (100)": "43.53",
            "GO (100)": "52.69",
            "OI (100)": "50.76",
            "PERCEPTION (100)": "6.48",
            "ranking_score": "47.84",
            "college_id": "IR-G-U-0259",
            "college_name": "Kerala University of Fisheries and Ocean Studies",
            "even href": "https://www.nirfindia.org/nirfpdfcdn/2024/pdf/Agriculture/IR-G-U-0259.pdf",
            "even href 2": "https://www.nirfindia.org/nirfpdfcdn/2024/graph/Agriculture/IR-G-U-0259.jpg",
            "college_city": "Kochi",
            "college_state": "Kerala",
            "college_rank": "30"
        },
        {
            "college_id": "IR-G-U-0336",
            "college_name": "Central Agricultural University",
            "odd href": "https://www.nirfindia.org/nirfpdfcdn/2024/pdf/Agriculture/IR-G-U-0336.pdf",
            "odd href 2": "https://www.nirfindia.org/nirfpdfcdn/2024/graph/Agriculture/IR-G-U-0336.jpg",
            "TLR (100)": "71.42",
            "RPC (100)": "26.45",
            "GO (100)": "51.98",
            "OI (100)": "54.06",
            "PERCEPTION (100)": "23.49",
            "college_city": "Imphal West",
            "college_state": "Manipur",
            "ranking_score": "47.53",
            "college_rank": "31"
        },
        {
            "TLR (100)": "66.51",
            "RPC (100)": "21.18",
            "GO (100)": "54.64",
            "OI (100)": "49.87",
            "PERCEPTION (100)": "42.41",
            "ranking_score": "46.46",
            "college_id": "IR-G-U-0665",
            "college_name": "Tamil Nadu Dr.J.Jayalalithaa Fisheries University",
            "even href": "https://www.nirfindia.org/nirfpdfcdn/2024/pdf/Agriculture/IR-G-U-0665.pdf",
            "even href 2": "https://www.nirfindia.org/nirfpdfcdn/2024/graph/Agriculture/IR-G-U-0665.jpg",
            "college_city": "Nagapattinam",
            "college_state": "Tamil Nadu",
            "college_rank": "32"
        },
        {
            "college_id": "IR-G-U-0039",
            "college_name": "Sri Venkateswara Veterinary University",
            "odd href": "https://www.nirfindia.org/nirfpdfcdn/2024/pdf/Agriculture/IR-G-U-0039.pdf",
            "odd href 2": "https://www.nirfindia.org/nirfpdfcdn/2024/graph/Agriculture/IR-G-U-0039.jpg",
            "TLR (100)": "70.75",
            "RPC (100)": "6.34",
            "GO (100)": "75.52",
            "OI (100)": "52.71",
            "PERCEPTION (100)": "29.08",
            "college_city": "Tirupati",
            "college_state": "Andhra Pradesh",
            "ranking_score": "46.41",
            "college_rank": "33"
        },
        {
            "TLR (100)": "82.21",
            "RPC (100)": "22.03",
            "GO (100)": "45.90",
            "OI (100)": "37.90",
            "PERCEPTION (100)": "19.29",
            "ranking_score": "46.17",
            "college_id": "IR-G-U-0165",
            "college_name": "Lala lajpat Rai University of Veterinary and Animal Sciences",
            "even href": "https://www.nirfindia.org/nirfpdfcdn/2024/pdf/Agriculture/IR-G-U-0165.pdf",
            "even href 2": "https://www.nirfindia.org/nirfpdfcdn/2024/graph/Agriculture/IR-G-U-0165.jpg",
            "college_city": "Hisar",
            "college_state": "Haryana",
            "college_rank": "34"
        },
        {
            "college_id": "IR-G-U-0145",
            "college_name": "Navsari Agricultural University",
            "odd href": "https://www.nirfindia.org/nirfpdfcdn/2024/pdf/Agriculture/IR-G-U-0145.pdf",
            "odd href 2": "https://www.nirfindia.org/nirfpdfcdn/2024/graph/Agriculture/IR-G-U-0145.jpg",
            "TLR (100)": "83.56",
            "RPC (100)": "8.93",
            "GO (100)": "59.36",
            "OI (100)": "45.78",
            "PERCEPTION (100)": "17.03",
            "college_city": "Navsari",
            "college_state": "Gujarat",
            "ranking_score": "45.90",
            "college_rank": "35"
        },
        {
            "TLR (100)": "74.50",
            "RPC (100)": "14.63",
            "GO (100)": "56.16",
            "OI (100)": "51.82",
            "PERCEPTION (100)": "25.44",
            "ranking_score": "45.69",
            "college_id": "IR-G-U-0060",
            "college_name": "Bihar Agriculture University",
            "even href": "https://www.nirfindia.org/nirfpdfcdn/2024/pdf/Agriculture/IR-G-U-0060.pdf",
            "even href 2": "https://www.nirfindia.org/nirfpdfcdn/2024/graph/Agriculture/IR-G-U-0060.jpg",
            "college_city": "Bhagalpur",
            "college_state": "Bihar",
            "college_rank": "36"
        },
        {
            "college_id": "IR-G-U-0784",
            "college_name": "Professor Jayashankar Telangana State Agricultural University",
            "odd href": "https://www.nirfindia.org/nirfpdfcdn/2024/pdf/Agriculture/IR-G-U-0784.pdf",
            "odd href 2": "https://www.nirfindia.org/nirfpdfcdn/2024/graph/Agriculture/IR-G-U-0784.jpg",
            "TLR (100)": "79.61",
            "RPC (100)": "10.44",
            "GO (100)": "47.99",
            "OI (100)": "53.87",
            "PERCEPTION (100)": "27.30",
            "college_city": "Hyderabad",
            "college_state": "Telangana",
            "ranking_score": "44.73",
            "college_rank": "37"
        },
        {
            "TLR (100)": "63.77",
            "RPC (100)": "22.54",
            "GO (100)": "38.37",
            "OI (100)": "85.32",
            "PERCEPTION (100)": "25.44",
            "ranking_score": "44.63",
            "college_id": "IR-G-U-0458",
            "college_name": "Kalasalingam Academy of Research and Education",
            "even href": "https://www.nirfindia.org/nirfpdfcdn/2024/pdf/Agriculture/IR-G-U-0458.pdf",
            "even href 2": "https://www.nirfindia.org/nirfpdfcdn/2024/graph/Agriculture/IR-G-U-0458.jpg",
            "college_city": "Srivilliputhur",
            "college_state": "Tamil Nadu",
            "college_rank": "38"
        },
        {
            "college_id": "IR-G-U-0087",
            "college_name": "Indira Gandhi Krishi Vishwavidyalaya",
            "odd href": "https://www.nirfindia.org/nirfpdfcdn/2024/pdf/Agriculture/IR-G-U-0087.pdf",
            "odd href 2": "https://www.nirfindia.org/nirfpdfcdn/2024/graph/Agriculture/IR-G-U-0087.jpg",
            "TLR (100)": "62.83",
            "RPC (100)": "13.22",
            "GO (100)": "74.41",
            "OI (100)": "47.43",
            "PERCEPTION (100)": "17.03",
            "college_city": "Raipur",
            "college_state": "Chhattisgarh",
            "ranking_score": "44.14",
            "college_rank": "39"
        },
        {
            "TLR (100)": "80.72",
            "RPC (100)": "13.98",
            "GO (100)": "52.66",
            "OI (100)": "27.53",
            "PERCEPTION (100)": "23.49",
            "ranking_score": "44.05",
            "college_id": "IR-G-U-0587",
            "college_name": "Uttar Banga Krishi Vishwavidyalaya",
            "even href": "https://www.nirfindia.org/nirfpdfcdn/2024/pdf/Agriculture/IR-G-U-0587.pdf",
            "even href 2": "https://www.nirfindia.org/nirfpdfcdn/2024/graph/Agriculture/IR-G-U-0587.jpg",
            "college_city": "Cooch Behar",
            "college_state": "West Bengal",
            "college_rank": "40"
        }
    ]
}