{
  "https://www.nirfindia.org/Ranki": [
    {
      "college_id": "IR-M-S-8890",
      "college_name": "Indian Institute of Management Ahmedabad",
      "odd href": "https://www.nirfindia.org/nirfpdfcdn/2024/pdf/Management/IR-M-S-8890.pdf",
      "odd href 2": "https://www.nirfindia.org/nirfpdfcdn/2024/graph/Management/IR-M-S-8890.jpg",
      "TLR (100)": "91.88",
      "RPC (100)": "63.89",
      "GO (100)": "98.71",
      "OI (100)": "71.72",
      "PERCEPTION (100)": "96.81",
      "college_city": "Ahmedabad",
      "college_state": "Gujarat",
      "sorting_1": "83.32",
      "college_rank": "1"
    },
    {
      "TLR (100)": "90.08",
      "RPC (100)": "56.71",
      "GO (100)": "98.41",
      "OI (100)": "74.54",
      "PERCEPTION (100)": "100.00",
      "sorting_1": "81.16",
      "college_id": "IR-M-S-8903",
      "college_name": "Indian Institute of Management Bangalore",
      "even href": "https://www.nirfindia.org/nirfpdfcdn/2024/pdf/Management/IR-M-S-8903.pdf",
      "even href 2": "https://www.nirfindia.org/nirfpdfcdn/2024/graph/Management/IR-M-S-8903.jpg",
      "college_city": "Bengaluru",
      "college_state": "Karnataka",
      "college_rank": "2"
    },
    {
      "college_id": "IR-M-S-8909",
      "college_name": "Indian Institute of Management Kozhikode",
      "odd href": "https://www.nirfindia.org/nirfpdfcdn/2024/pdf/Management/IR-M-S-8909.pdf",
      "odd href 2": "https://www.nirfindia.org/nirfpdfcdn/2024/graph/Management/IR-M-S-8909.jpg",
      "TLR (100)": "86.99",
      "RPC (100)": "58.96",
      "GO (100)": "94.37",
      "OI (100)": "77.10",
      "PERCEPTION (100)": "75.30",
      "college_city": "Kozhikode",
      "college_state": "Kerala",
      "sorting_1": "77.90",
      "college_rank": "3"
    },
    {
      "TLR (100)": "72.21",
      "RPC (100)": "78.39",
      "GO (100)": "89.51",
      "OI (100)": "67.37",
      "PERCEPTION (100)": "64.25",
      "sorting_1": "76.25",
      "college_id": "IR-M-I-1074",
      "college_name": "Indian Institute of Technology Delhi",
      "even href": "https://www.nirfindia.org/nirfpdfcdn/2024/pdf/Management/IR-M-I-1074.pdf",
      "even href 2": "https://www.nirfindia.org/nirfpdfcdn/2024/graph/Management/IR-M-I-1074.jpg",
      "college_city": "New Delhi",
      "college_state": "Delhi",
      "college_rank": "4"
    },
    {
      "college_id": "IR-M-S-8972",
      "college_name": "Indian Institute of Management Calcutta",
      "odd href": "https://www.nirfindia.org/nirfpdfcdn/2024/pdf/Management/IR-M-S-8972.pdf",
      "odd href 2": "https://www.nirfindia.org/nirfpdfcdn/2024/graph/Management/IR-M-S-8972.jpg",
      "TLR (100)": "84.12",
      "RPC (100)": "48.09",
      "GO (100)": "99.09",
      "OI (100)": "70.46",
      "PERCEPTION (100)": "85.29",
      "college_city": "Kolkata",
      "college_state": "West Bengal",
      "sorting_1": "75.07",
      "college_rank": "5"
    },
    {
      "TLR (100)": "80.81",
      "RPC (100)": "59.14",
      "GO (100)": "99.41",
      "OI (100)": "75.86",
      "PERCEPTION (100)": "52.82",
      "sorting_1": "74.73",
      "college_id": "IR-M-S-8931",
      "college_name": "Indian Institute of Management Mumbai",
      "even href": "https://www.nirfindia.org/nirfpdfcdn/2024/pdf/Management/IR-M-S-8931.pdf",
      "even href 2": "https://www.nirfindia.org/nirfpdfcdn/2024/graph/Management/IR-M-S-8931.jpg",
      "college_city": "Mumbai",
      "college_state": "Maharashtra",
      "college_rank": "6"
    },
    {
      "college_id": "IR-M-S-8959",
      "college_name": "Indian Institute of Management Lucknow",
      "odd href": "https://www.nirfindia.org/nirfpdfcdn/2024/pdf/Management/IR-M-S-8959.pdf",
      "odd href 2": "https://www.nirfindia.org/nirfpdfcdn/2024/graph/Management/IR-M-S-8959.jpg",
      "TLR (100)": "84.25",
      "RPC (100)": "49.09",
      "GO (100)": "96.59",
      "OI (100)": "71.17",
      "PERCEPTION (100)": "79.81",
      "college_city": "Lucknow",
      "college_state": "Uttar Pradesh",
      "sorting_1": "74.43",
      "college_rank": "7"
    },
    {
      "TLR (100)": "84.08",
      "RPC (100)": "55.28",
      "GO (100)": "93.49",
      "OI (100)": "72.38",
      "PERCEPTION (100)": "57.93",
      "sorting_1": "73.53",
      "college_id": "IR-M-S-8918",
      "college_name": "Indian Institute of Management Indore",
      "even href": "https://www.nirfindia.org/nirfpdfcdn/2024/pdf/Management/IR-M-S-8918.pdf",
      "even href 2": "https://www.nirfindia.org/nirfpdfcdn/2024/graph/Management/IR-M-S-8918.jpg",
      "college_city": "Indore",
      "college_state": "Madhya Pradesh",
      "college_rank": "8"
    },
    {
      "college_id": "IR-M-S-132",
      "college_name": "XLRI - Xavier School of Management",
      "odd href": "https://www.nirfindia.org/nirfpdfcdn/2024/pdf/Management/IR-M-S-132.pdf",
      "odd href 2": "https://www.nirfindia.org/nirfpdfcdn/2024/graph/Management/IR-M-S-132.jpg",
      "TLR (100)": "85.49",
      "RPC (100)": "39.79",
      "GO (100)": "97.92",
      "OI (100)": "64.57",
      "PERCEPTION (100)": "45.02",
      "college_city": "Jamshedpur",
      "college_state": "Jharkhand",
      "sorting_1": "68.13",
      "college_rank": "9"
    },
    {
      "TLR (100)": "78.30",
      "RPC (100)": "61.64",
      "GO (100)": "79.25",
      "OI (100)": "58.83",
      "PERCEPTION (100)": "34.50",
      "sorting_1": "67.16",
      "college_id": "IR-M-U-0306",
      "college_name": "Indian Institute of Technology Bombay",
      "even href": "https://www.nirfindia.org/nirfpdfcdn/2024/pdf/Management/IR-M-U-0306.pdf",
      "even href 2": "https://www.nirfindia.org/nirfpdfcdn/2024/graph/Management/IR-M-U-0306.jpg",
      "college_city": "Mumbai",
      "college_state": "Maharashtra",
      "college_rank": "10"
    },
    {
      "college_id": "IR-M-I-1170",
      "college_name": "Management Development Institute",
      "odd href": "https://www.nirfindia.org/nirfpdfcdn/2024/pdf/Management/IR-M-I-1170.pdf",
      "odd href 2": "https://www.nirfindia.org/nirfpdfcdn/2024/graph/Management/IR-M-I-1170.jpg",
      "TLR (100)": "75.87",
      "RPC (100)": "50.74",
      "GO (100)": "95.24",
      "OI (100)": "71.05",
      "PERCEPTION (100)": "27.07",
      "college_city": "Gurugram",
      "college_state": "Haryana",
      "sorting_1": "66.85",
      "college_rank": "11"
    },
    {
      "TLR (100)": "79.69",
      "RPC (100)": "45.01",
      "GO (100)": "88.90",
      "OI (100)": "75.98",
      "PERCEPTION (100)": "37.00",
      "sorting_1": "66.49",
      "college_id": "IR-M-S-8895",
      "college_name": "Indian Institute of Management Rohtak",
      "even href": "https://www.nirfindia.org/nirfpdfcdn/2024/pdf/Management/IR-M-S-8895.pdf",
      "even href 2": "https://www.nirfindia.org/nirfpdfcdn/2024/graph/Management/IR-M-S-8895.jpg",
      "college_city": "Rohtak",
      "college_state": "Haryana",
      "college_rank": "12"
    },
    {
      "college_id": "IR-M-C-19343",
      "college_name": "Symbiosis Institute of Business Management",
      "odd href": "https://www.nirfindia.org/nirfpdfcdn/2024/pdf/Management/IR-M-C-19343.pdf",
      "odd href 2": "https://www.nirfindia.org/nirfpdfcdn/2024/graph/Management/IR-M-C-19343.jpg",
      "TLR (100)": "75.51",
      "RPC (100)": "42.85",
      "GO (100)": "94.27",
      "OI (100)": "66.50",
      "PERCEPTION (100)": "41.21",
      "college_city": "Pune",
      "college_state": "Maharashtra",
      "sorting_1": "65.13",
      "college_rank": "13"
    },
    {
      "TLR (100)": "78.31",
      "RPC (100)": "41.28",
      "GO (100)": "90.68",
      "OI (100)": "80.55",
      "PERCEPTION (100)": "23.25",
      "sorting_1": "64.40",
      "college_id": "IR-M-S-8868",
      "college_name": "Indian Institute of Management Raipur",
      "even href": "https://www.nirfindia.org/nirfpdfcdn/2024/pdf/Management/IR-M-S-8868.pdf",
      "even href 2": "https://www.nirfindia.org/nirfpdfcdn/2024/graph/Management/IR-M-S-8868.jpg",
      "college_city": "Raipur",
      "college_state": "Chhattisgarh",
      "college_rank": "14"
    },
    {
      "college_id": "IR-M-U-0102",
      "college_name": "Indian Institute of Foreign Trade",
      "odd href": "https://www.nirfindia.org/nirfpdfcdn/2024/pdf/Management/IR-M-U-0102.pdf",
      "odd href 2": "https://www.nirfindia.org/nirfpdfcdn/2024/graph/Management/IR-M-U-0102.jpg",
      "TLR (100)": "80.36",
      "RPC (100)": "32.80",
      "GO (100)": "87.48",
      "OI (100)": "66.49",
      "PERCEPTION (100)": "42.58",
      "college_city": "New Delhi",
      "college_state": "Delhi",
      "sorting_1": "62.36",
      "college_rank": "15"
    },
    {
      "TLR (100)": "70.39",
      "RPC (100)": "47.93",
      "GO (100)": "75.10",
      "OI (100)": "60.43",
      "PERCEPTION (100)": "51.74",
      "sorting_1": "61.73",
      "college_id": "IR-M-U-0456",
      "college_name": "Indian Institute of Technology Madras",
      "even href": "https://www.nirfindia.org/nirfpdfcdn/2024/pdf/Management/IR-M-U-0456.pdf",
      "even href 2": "https://www.nirfindia.org/nirfpdfcdn/2024/graph/Management/IR-M-U-0456.jpg",
      "college_city": "Chennai",
      "college_state": "Tamil Nadu",
      "college_rank": "16"
    },
    {
      "college_id": "IR-M-S-8904",
      "college_name": "Indian Institute of Management Ranchi",
      "odd href": "https://www.nirfindia.org/nirfpdfcdn/2024/pdf/Management/IR-M-S-8904.pdf",
      "odd href 2": "https://www.nirfindia.org/nirfpdfcdn/2024/graph/Management/IR-M-S-8904.jpg",
      "TLR (100)": "70.89",
      "RPC (100)": "39.65",
      "GO (100)": "89.45",
      "OI (100)": "71.42",
      "PERCEPTION (100)": "30.82",
      "college_city": "Ranchi",
      "college_state": "Jharkhand",
      "sorting_1": "61.27",
      "college_rank": "17"
    },
    {
      "TLR (100)": "68.08",
      "RPC (100)": "59.00",
      "GO (100)": "71.09",
      "OI (100)": "62.16",
      "PERCEPTION (100)": "26.50",
      "sorting_1": "61.21",
      "college_id": "IR-M-U-0560",
      "college_name": "Indian Institute of Technology Roorkee",
      "even href": "https://www.nirfindia.org/nirfpdfcdn/2024/pdf/Management/IR-M-U-0560.pdf",
      "even href 2": "https://www.nirfindia.org/nirfpdfcdn/2024/graph/Management/IR-M-U-0560.jpg",
      "college_city": "Roorkee",
      "college_state": "Uttarakhand",
      "college_rank": "18"
    },
    {
      "college_id": "IR-M-U-0573",
      "college_name": "Indian Institute of Technology Kharagpur",
      "odd href": "https://www.nirfindia.org/nirfpdfcdn/2024/pdf/Management/IR-M-U-0573.pdf",
      "odd href 2": "https://www.nirfindia.org/nirfpdfcdn/2024/graph/Management/IR-M-U-0573.jpg",
      "TLR (100)": "50.10",
      "RPC (100)": "63.68",
      "GO (100)": "87.88",
      "OI (100)": "55.17",
      "PERCEPTION (100)": "37.88",
      "college_city": "Kharagpur",
      "college_state": "West Bengal",
      "sorting_1": "61.03",
      "college_rank": "19"
    },
    {
      "TLR (100)": "78.86",
      "RPC (100)": "26.60",
      "GO (100)": "98.65",
      "OI (100)": "68.90",
      "PERCEPTION (100)": "27.07",
      "sorting_1": "60.97",
      "college_id": "IR-M-I-1044",
      "college_name": "S. P. Jain Institute of Management and Research",
      "even href": "https://www.nirfindia.org/nirfpdfcdn/2024/pdf/Management/IR-M-I-1044.pdf",
      "even href 2": "https://www.nirfindia.org/nirfpdfcdn/2024/graph/Management/IR-M-I-1044.jpg",
      "college_city": "Mumbai",
      "college_state": "Maharashtra",
      "college_rank": "20"
    },
    {
      "college_id": "IR-M-N-10",
      "college_name": "SVKM`s Narsee Monjee Institute of Management Studies",
      "odd href": "https://www.nirfindia.org/nirfpdfcdn/2024/pdf/Management/IR-M-N-10.pdf",
      "odd href 2": "https://www.nirfindia.org/nirfpdfcdn/2024/graph/Management/IR-M-N-10.jpg",
      "TLR (100)": "78.42",
      "RPC (100)": "29.96",
      "GO (100)": "92.39",
      "OI (100)": "76.71",
      "PERCEPTION (100)": "22.95",
      "college_city": "Mumbai",
      "college_state": "Maharashtra",
      "sorting_1": "60.96",
      "college_rank": "21"
    },
    {
      "TLR (100)": "79.21",
      "RPC (100)": "33.95",
      "GO (100)": "88.69",
      "OI (100)": "72.05",
      "PERCEPTION (100)": "20.39",
      "sorting_1": "60.93",
      "college_id": "IR-M-S-8942",
      "college_name": "Indian Institute of Management Udaipur",
      "even href": "https://www.nirfindia.org/nirfpdfcdn/2024/pdf/Management/IR-M-S-8942.pdf",
      "even href 2": "https://www.nirfindia.org/nirfpdfcdn/2024/graph/Management/IR-M-S-8942.jpg",
      "college_city": "Udaipur",
      "college_state": "Rajasthan",
      "college_rank": "22"
    },
    {
      "college_id": "IR-M-S-8967",
      "college_name": "Indian Institute of Management Kashipur",
      "odd href": "https://www.nirfindia.org/nirfpdfcdn/2024/pdf/Management/IR-M-S-8967.pdf",
      "odd href 2": "https://www.nirfindia.org/nirfpdfcdn/2024/graph/Management/IR-M-S-8967.jpg",
      "TLR (100)": "67.95",
      "RPC (100)": "40.39",
      "GO (100)": "89.06",
      "OI (100)": "74.47",
      "PERCEPTION (100)": "30.56",
      "college_city": "Kashipur",
      "college_state": "Uttarakhand",
      "sorting_1": "60.82",
      "college_rank": "23"
    },
    {
      "TLR (100)": "74.68",
      "RPC (100)": "28.33",
      "GO (100)": "94.96",
      "OI (100)": "74.09",
      "PERCEPTION (100)": "31.83",
      "sorting_1": "60.49",
      "college_id": "IR-M-S-8937",
      "college_name": "Indian Institute of Management Shillong",
      "even href": "https://www.nirfindia.org/nirfpdfcdn/2024/pdf/Management/IR-M-S-8937.pdf",
      "even href 2": "https://www.nirfindia.org/nirfpdfcdn/2024/graph/Management/IR-M-S-8937.jpg",
      "college_city": "Shillong",
      "college_state": "Meghalaya",
      "college_rank": "24"
    },
    {
      "college_id": "IR-M-U-0108",
      "college_name": "Jamia Millia Islamia",
      "odd href": "https://www.nirfindia.org/nirfpdfcdn/2024/pdf/Management/IR-M-U-0108.pdf",
      "odd href 2": "https://www.nirfindia.org/nirfpdfcdn/2024/graph/Management/IR-M-U-0108.jpg",
      "TLR (100)": "65.45",
      "RPC (100)": "48.39",
      "GO (100)": "81.46",
      "OI (100)": "83.65",
      "PERCEPTION (100)": "15.14",
      "college_city": "New Delhi",
      "college_state": "Delhi",
      "sorting_1": "60.32",
      "college_rank": "25"
    },
    {
      "TLR (100)": "80.81",
      "RPC (100)": "22.51",
      "GO (100)": "86.10",
      "OI (100)": "70.53",
      "PERCEPTION (100)": "39.37",
      "sorting_1": "59.20",
      "college_id": "IR-M-U-1007",
      "college_name": "Indian Institute of Management Visakhapatnam",
      "even href": "https://www.nirfindia.org/nirfpdfcdn/2024/pdf/Management/IR-M-U-1007.pdf",
      "even href 2": "https://www.nirfindia.org/nirfpdfcdn/2024/graph/Management/IR-M-U-1007.jpg",
      "college_city": "Visakhapatnam",
      "college_state": "Andhra Pradesh",
      "college_rank": "26"
    },
    {
      "college_id": "IR-M-S-8948",
      "college_name": "Indian Institute of Management Tiruchirappalli",
      "odd href": "https://www.nirfindia.org/nirfpdfcdn/2024/pdf/Management/IR-M-S-8948.pdf",
      "odd href 2": "https://www.nirfindia.org/nirfpdfcdn/2024/graph/Management/IR-M-S-8948.jpg",
      "TLR (100)": "60.97",
      "RPC (100)": "29.09",
      "GO (100)": "87.47",
      "OI (100)": "69.74",
      "PERCEPTION (100)": "61.89",
      "college_city": "Tiruchirappalli",
      "college_state": "Tamil Nadu",
      "sorting_1": "57.67",
      "college_rank": "27"
    },
    {
      "TLR (100)": "64.11",
      "RPC (100)": "41.40",
      "GO (100)": "73.51",
      "OI (100)": "75.50",
      "PERCEPTION (100)": "34.97",
      "sorting_1": "57.40",
      "college_id": "IR-M-U-0436",
      "college_name": "Amrita Vishwa Vidyapeetham",
      "even href": "https://www.nirfindia.org/nirfpdfcdn/2024/pdf/Management/IR-M-U-0436.pdf",
      "even href 2": "https://www.nirfindia.org/nirfpdfcdn/2024/graph/Management/IR-M-U-0436.jpg",
      "college_city": "Coimbatore",
      "college_state": "Tamil Nadu",
      "college_rank": "28"
    },
    {
      "college_id": "IR-M-U-0497",
      "college_name": "Amity University",
      "odd href": "https://www.nirfindia.org/nirfpdfcdn/2024/pdf/Management/IR-M-U-0497.pdf",
      "odd href 2": "https://www.nirfindia.org/nirfpdfcdn/2024/graph/Management/IR-M-U-0497.jpg",
      "TLR (100)": "70.39",
      "RPC (100)": "54.11",
      "GO (100)": "58.85",
      "OI (100)": "67.49",
      "PERCEPTION (100)": "13.62",
      "college_city": "Gautam Budh Nagar",
      "college_state": "Uttar Pradesh",
      "sorting_1": "57.23",
      "college_rank": "29"
    },
    {
      "TLR (100)": "66.90",
      "RPC (100)": "44.97",
      "GO (100)": "77.90",
      "OI (100)": "48.81",
      "PERCEPTION (100)": "32.08",
      "sorting_1": "57.23",
      "college_id": "IR-M-I-1075",
      "college_name": "Indian Institute of Technology Kanpur",
      "even href": "https://www.nirfindia.org/nirfpdfcdn/2024/pdf/Management/IR-M-I-1075.pdf",
      "even href 2": "https://www.nirfindia.org/nirfpdfcdn/2024/graph/Management/IR-M-I-1075.jpg",
      "college_city": "Kanpur",
      "college_state": "Uttar Pradesh",
      "college_rank": "29"
    },
    {
      "college_id": "IR-M-S-15962",
      "college_name": "Indian Institute of Management Nagpur",
      "odd href": "https://www.nirfindia.org/nirfpdfcdn/2024/pdf/Management/IR-M-S-15962.pdf",
      "odd href 2": "https://www.nirfindia.org/nirfpdfcdn/2024/graph/Management/IR-M-S-15962.jpg",
      "TLR (100)": "71.57",
      "RPC (100)": "27.17",
      "GO (100)": "86.55",
      "OI (100)": "70.33",
      "PERCEPTION (100)": "29.78",
      "college_city": "Nagpur",
      "college_state": "Maharashtra",
      "sorting_1": "56.94",
      "college_rank": "31"
    },
    {
      "TLR (100)": "70.52",
      "RPC (100)": "38.08",
      "GO (100)": "84.36",
      "OI (100)": "68.13",
      "PERCEPTION (100)": "3.60",
      "sorting_1": "56.62",
      "college_id": "IR-M-S-14875",
      "college_name": "MICA",
      "even href": "https://www.nirfindia.org/nirfpdfcdn/2024/pdf/Management/IR-M-S-14875.pdf",
      "even href 2": "https://www.nirfindia.org/nirfpdfcdn/2024/graph/Management/IR-M-S-14875.jpg",
      "college_city": "Ahmedabad",
      "college_state": "Gujarat",
      "college_rank": "32"
    },
    {
      "college_id": "IR-M-U-1006",
      "college_name": "Indian Institute of Management Bodh Gaya",
      "odd href": "https://www.nirfindia.org/nirfpdfcdn/2024/pdf/Management/IR-M-U-1006.pdf",
      "odd href 2": "https://www.nirfindia.org/nirfpdfcdn/2024/graph/Management/IR-M-U-1006.jpg",
      "TLR (100)": "75.08",
      "RPC (100)": "25.80",
      "GO (100)": "84.73",
      "OI (100)": "69.59",
      "PERCEPTION (100)": "21.05",
      "college_city": "Gaya",
      "college_state": "Bihar",
      "sorting_1": "56.27",
      "college_rank": "33"
    },
    {
      "TLR (100)": "78.30",
      "RPC (100)": "22.05",
      "GO (100)": "81.85",
      "OI (100)": "73.36",
      "PERCEPTION (100)": "23.25",
      "sorting_1": "56.15",
      "college_id": "IR-M-N-16",
      "college_name": "Great Lakes Institute of Management",
      "even href": "https://www.nirfindia.org/nirfpdfcdn/2024/pdf/Management/IR-M-N-16.pdf",
      "even href 2": "https://www.nirfindia.org/nirfpdfcdn/2024/graph/Management/IR-M-N-16.jpg",
      "college_city": "Chennai",
      "college_state": "Tamil Nadu",
      "college_rank": "34"
    },
    {
      "college_id": "IR-M-S-394",
      "college_name": "Institute of Management Technology",
      "odd href": "https://www.nirfindia.org/nirfpdfcdn/2024/pdf/Management/IR-M-S-394.pdf",
      "odd href 2": "https://www.nirfindia.org/nirfpdfcdn/2024/graph/Management/IR-M-S-394.jpg",
      "TLR (100)": "76.46",
      "RPC (100)": "32.51",
      "GO (100)": "80.64",
      "OI (100)": "63.76",
      "PERCEPTION (100)": "8.25",
      "college_city": "Ghaziabad",
      "college_state": "Uttar Pradesh",
      "sorting_1": "56.03",
      "college_rank": "35"
    },
    {
      "TLR (100)": "75.30",
      "RPC (100)": "30.03",
      "GO (100)": "70.22",
      "OI (100)": "80.58",
      "PERCEPTION (100)": "20.06",
      "sorting_1": "55.71",
      "college_id": "IR-M-U-0747",
      "college_name": "Chandigarh University",
      "even href": "https://www.nirfindia.org/nirfpdfcdn/2024/pdf/Management/IR-M-U-0747.pdf",
      "even href 2": "https://www.nirfindia.org/nirfpdfcdn/2024/graph/Management/IR-M-U-0747.jpg",
      "college_city": "Mohali",
      "college_state": "Punjab",
      "college_rank": "36"
    },
    {
      "college_id": "IR-M-S-87",
      "college_name": "Goa Institute of Management",
      "odd href": "https://www.nirfindia.org/nirfpdfcdn/2024/pdf/Management/IR-M-S-87.pdf",
      "odd href 2": "https://www.nirfindia.org/nirfpdfcdn/2024/graph/Management/IR-M-S-87.jpg",
      "TLR (100)": "75.11",
      "RPC (100)": "25.94",
      "GO (100)": "84.41",
      "OI (100)": "71.65",
      "PERCEPTION (100)": "13.23",
      "college_city": "Sanquelim",
      "college_state": "Goa",
      "sorting_1": "55.67",
      "college_rank": "37"
    },
    {
      "TLR (100)": "73.49",
      "RPC (100)": "38.97",
      "GO (100)": "62.87",
      "OI (100)": "75.19",
      "PERCEPTION (100)": "16.61",
      "sorting_1": "55.49",
      "college_id": "IR-M-U-0379",
      "college_name": "Lovely Professional University",
      "even href": "https://www.nirfindia.org/nirfpdfcdn/2024/pdf/Management/IR-M-U-0379.pdf",
      "even href 2": "https://www.nirfindia.org/nirfpdfcdn/2024/graph/Management/IR-M-U-0379.jpg",
      "college_city": "Phagwara",
      "college_state": "Punjab",
      "college_rank": "38"
    },
    {
      "college_id": "IR-M-U-0012",
      "college_name": "ICFAI Foundation for Higher Education, Hyderabad",
      "odd href": "https://www.nirfindia.org/nirfpdfcdn/2024/pdf/Management/IR-M-U-0012.pdf",
      "odd href 2": "https://www.nirfindia.org/nirfpdfcdn/2024/graph/Management/IR-M-U-0012.jpg",
      "TLR (100)": "75.59",
      "RPC (100)": "26.77",
      "GO (100)": "75.96",
      "OI (100)": "76.06",
      "PERCEPTION (100)": "18.02",
      "college_city": "Hyderabad",
      "college_state": "Telangana",
      "sorting_1": "55.31",
      "college_rank": "39"
    },
    {
      "TLR (100)": "72.25",
      "RPC (100)": "26.29",
      "GO (100)": "87.23",
      "OI (100)": "69.58",
      "PERCEPTION (100)": "9.12",
      "sorting_1": "54.89",
      "college_id": "IR-M-I-1064",
      "college_name": "International Management Institute",
      "even href": "https://www.nirfindia.org/nirfpdfcdn/2024/pdf/Management/IR-M-I-1064.pdf",
      "even href 2": "https://www.nirfindia.org/nirfpdfcdn/2024/graph/Management/IR-M-I-1064.jpg",
      "college_city": "New Delhi",
      "college_state": "Delhi",
      "college_rank": "40"
    },
    {
      "college_id": "IR-M-U-0564",
      "college_name": "UPES",
      "odd href": "https://www.nirfindia.org/nirfpdfcdn/2024/pdf/Management/IR-M-U-0564.pdf",
      "odd href 2": "https://www.nirfindia.org/nirfpdfcdn/2024/graph/Management/IR-M-U-0564.jpg",
      "TLR (100)": "73.29",
      "RPC (100)": "32.94",
      "GO (100)": "67.39",
      "OI (100)": "65.68",
      "PERCEPTION (100)": "28.99",
      "college_city": "Dehradun",
      "college_state": "Uttarakhand",
      "sorting_1": "54.82",
      "college_rank": "41"
    },
    {
      "TLR (100)": "73.73",
      "RPC (100)": "16.68",
      "GO (100)": "86.87",
      "OI (100)": "73.31",
      "PERCEPTION (100)": "28.18",
      "sorting_1": "54.64",
      "college_id": "IR-M-U-1004",
      "college_name": "Indian Institute of Management Jammu (IIMJ)",
      "even href": "https://www.nirfindia.org/nirfpdfcdn/2024/pdf/Management/IR-M-U-1004.pdf",
      "even href 2": "https://www.nirfindia.org/nirfpdfcdn/2024/graph/Management/IR-M-U-1004.jpg",
      "college_city": "Jammu",
      "college_state": "Jammu and Kashmir",
      "college_rank": "42"
    },
    {
      "college_id": "IR-M-U-0715",
      "college_name": "XIM University",
      "odd href": "https://www.nirfindia.org/nirfpdfcdn/2024/pdf/Management/IR-M-U-0715.pdf",
      "odd href 2": "https://www.nirfindia.org/nirfpdfcdn/2024/graph/Management/IR-M-U-0715.jpg",
      "TLR (100)": "73.86",
      "RPC (100)": "21.36",
      "GO (100)": "91.24",
      "OI (100)": "55.04",
      "PERCEPTION (100)": "21.69",
      "college_city": "Bhubaneswar",
      "college_state": "Odisha",
      "sorting_1": "54.49",
      "college_rank": "43"
    },
    {
      "TLR (100)": "66.13",
      "RPC (100)": "42.28",
      "GO (100)": "63.22",
      "OI (100)": "72.33",
      "PERCEPTION (100)": "8.69",
      "sorting_1": "53.26",
      "college_id": "IR-M-I-1480",
      "college_name": "Thapar Institute of Engineering and Technology (Deemed-to-be-university)",
      "even href": "https://www.nirfindia.org/nirfpdfcdn/2024/pdf/Management/IR-M-I-1480.pdf",
      "even href 2": "https://www.nirfindia.org/nirfpdfcdn/2024/graph/Management/IR-M-I-1480.jpg",
      "college_city": "Patiala",
      "college_state": "Punjab",
      "college_rank": "44"
    },
    {
      "college_id": "IR-M-S-3283",
      "college_name": "Jaipuria Institute of Management",
      "odd href": "https://www.nirfindia.org/nirfpdfcdn/2024/pdf/Management/IR-M-S-3283.pdf",
      "odd href 2": "https://www.nirfindia.org/nirfpdfcdn/2024/graph/Management/IR-M-S-3283.jpg",
      "TLR (100)": "67.35",
      "RPC (100)": "28.22",
      "GO (100)": "76.47",
      "OI (100)": "67.15",
      "PERCEPTION (100)": "25.35",
      "college_city": "Noida",
      "college_state": "Uttar Pradesh",
      "sorting_1": "53.23",
      "college_rank": "45"
    },
    {
      "TLR (100)": "70.67",
      "RPC (100)": "41.31",
      "GO (100)": "55.53",
      "OI (100)": "63.79",
      "PERCEPTION (100)": "16.96",
      "sorting_1": "52.78",
      "college_id": "IR-M-U-0205",
      "college_name": "Indian Institute of Technology (Indian School of Mines) Dhanbad",
      "even href": "https://www.nirfindia.org/nirfpdfcdn/2024/pdf/Management/IR-M-U-0205.pdf",
      "even href 2": "https://www.nirfindia.org/nirfpdfcdn/2024/graph/Management/IR-M-U-0205.jpg",
      "college_city": "Dhanbad",
      "college_state": "Jharkhand",
      "college_rank": "46"
    },
    {
      "college_id": "IR-M-S-16881",
      "college_name": "Indian Institute of Management Amritsar",
      "odd href": "https://www.nirfindia.org/nirfpdfcdn/2024/pdf/Management/IR-M-S-16881.pdf",
      "odd href 2": "https://www.nirfindia.org/nirfpdfcdn/2024/graph/Management/IR-M-S-16881.jpg",
      "TLR (100)": "67.83",
      "RPC (100)": "18.63",
      "GO (100)": "87.86",
      "OI (100)": "67.99",
      "PERCEPTION (100)": "22.63",
      "college_city": "Amritsar",
      "college_state": "Punjab",
      "sorting_1": "52.57",
      "college_rank": "47"
    },
    {
      "TLR (100)": "62.18",
      "RPC (100)": "29.50",
      "GO (100)": "81.82",
      "OI (100)": "56.41",
      "PERCEPTION (100)": "27.63",
      "sorting_1": "52.26",
      "college_id": "IR-M-U-0500",
      "college_name": "Banaras Hindu University",
      "even href": "https://www.nirfindia.org/nirfpdfcdn/2024/pdf/Management/IR-M-U-0500.pdf",
      "even href 2": "https://www.nirfindia.org/nirfpdfcdn/2024/graph/Management/IR-M-U-0500.jpg",
      "college_city": "Varanasi",
      "college_state": "Uttar Pradesh",
      "college_rank": "48"
    },
    {
      "college_id": "IR-M-S-92",
      "college_name": "Institute of Rural Management Anand (IRMA)",
      "odd href": "https://www.nirfindia.org/nirfpdfcdn/2024/pdf/Management/IR-M-S-92.pdf",
      "odd href 2": "https://www.nirfindia.org/nirfpdfcdn/2024/graph/Management/IR-M-S-92.jpg",
      "TLR (100)": "65.29",
      "RPC (100)": "22.36",
      "GO (100)": "87.73",
      "OI (100)": "64.13",
      "PERCEPTION (100)": "12.84",
      "college_city": "Anand",
      "college_state": "Gujarat",
      "sorting_1": "51.54",
      "college_rank": "49"
    },
    {
      "TLR (100)": "64.06",
      "RPC (100)": "18.02",
      "GO (100)": "81.32",
      "OI (100)": "75.56",
      "PERCEPTION (100)": "30.31",
      "sorting_1": "51.47",
      "college_id": "IR-M-S-6",
      "college_name": "Indian Institute of Management Sambalpur",
      "even href": "https://www.nirfindia.org/nirfpdfcdn/2024/pdf/Management/IR-M-S-6.pdf",
      "even href 2": "https://www.nirfindia.org/nirfpdfcdn/2024/graph/Management/IR-M-S-6.jpg",
      "college_city": "Sambalpur",
      "college_state": "Odisha",
      "college_rank": "50"
    },
    {
      "college_id": "IR-M-U-0467",
      "college_name": "National Institute of Technology Tiruchirappalli",
      "odd href": "https://www.nirfindia.org/nirfpdfcdn/2024/pdf/Management/IR-M-U-0467.pdf",
      "odd href 2": "https://www.nirfindia.org/nirfpdfcdn/2024/graph/Management/IR-M-U-0467.jpg",
      "TLR (100)": "54.19",
      "RPC (100)": "39.84",
      "GO (100)": "71.84",
      "OI (100)": "61.66",
      "PERCEPTION (100)": "26.50",
      "college_city": "Tiruchirappalli",
      "college_state": "Tamil Nadu",
      "sorting_1": "51.40",
      "college_rank": "51"
    },
    {
      "TLR (100)": "76.53",
      "RPC (100)": "18.83",
      "GO (100)": "72.51",
      "OI (100)": "79.25",
      "PERCEPTION (100)": "3.10",
      "sorting_1": "51.35",
      "college_id": "IR-M-S-17295",
      "college_name": "Great Lakes Institute of Management",
      "even href": "https://www.nirfindia.org/nirfpdfcdn/2024/pdf/Management/IR-M-S-17295.pdf",
      "even href 2": "https://www.nirfindia.org/nirfpdfcdn/2024/graph/Management/IR-M-S-17295.jpg",
      "college_city": "Gurgaon",
      "college_state": "Haryana",
      "college_rank": "52"
    },
    {
      "college_id": "IR-M-I-1066",
      "college_name": "Fore School of Management",
      "odd href": "https://www.nirfindia.org/nirfpdfcdn/2024/pdf/Management/IR-M-I-1066.pdf",
      "odd href 2": "https://www.nirfindia.org/nirfpdfcdn/2024/graph/Management/IR-M-I-1066.jpg",
      "TLR (100)": "70.42",
      "RPC (100)": "17.93",
      "GO (100)": "85.12",
      "OI (100)": "62.40",
      "PERCEPTION (100)": "13.23",
      "college_city": "New Delhi",
      "college_state": "Delhi",
      "sorting_1": "51.08",
      "college_rank": "53"
    },
    {
      "TLR (100)": "71.22",
      "RPC (100)": "33.81",
      "GO (100)": "57.30",
      "OI (100)": "75.06",
      "PERCEPTION (100)": "5.52",
      "sorting_1": "51.02",
      "college_id": "IR-M-U-0373",
      "college_name": "Chitkara University",
      "even href": "https://www.nirfindia.org/nirfpdfcdn/2024/pdf/Management/IR-M-U-0373.pdf",
      "even href 2": "https://www.nirfindia.org/nirfpdfcdn/2024/graph/Management/IR-M-U-0373.jpg",
      "college_city": "Rajpura",
      "college_state": "Punjab",
      "college_rank": "54"
    },
    {
      "college_id": "IR-M-U-0146",
      "college_name": "Nirma University",
      "odd href": "https://www.nirfindia.org/nirfpdfcdn/2024/pdf/Management/IR-M-U-0146.pdf",
      "odd href 2": "https://www.nirfindia.org/nirfpdfcdn/2024/graph/Management/IR-M-U-0146.jpg",
      "TLR (100)": "64.09",
      "RPC (100)": "27.69",
      "GO (100)": "80.98",
      "OI (100)": "63.98",
      "PERCEPTION (100)": "8.69",
      "college_city": "Ahmedabad",
      "college_state": "Gujarat",
      "sorting_1": "51.01",
      "college_rank": "55"
    },
    {
      "TLR (100)": "63.64",
      "RPC (100)": "30.94",
      "GO (100)": "79.30",
      "OI (100)": "66.28",
      "PERCEPTION (100)": "1.06",
      "sorting_1": "50.97",
      "college_id": "IR-M-I-1408",
      "college_name": "International Management Institute, Kolkata",
      "even href": "https://www.nirfindia.org/nirfpdfcdn/2024/pdf/Management/IR-M-I-1408.pdf",
      "even href 2": "https://www.nirfindia.org/nirfpdfcdn/2024/graph/Management/IR-M-I-1408.jpg",
      "college_city": "Kolkata",
      "college_state": "West Bengal",
      "college_rank": "56"
    },
    {
      "college_id": "IR-M-S-15911",
      "college_name": "Indian Institute of Management Sirmaur",
      "odd href": "https://www.nirfindia.org/nirfpdfcdn/2024/pdf/Management/IR-M-S-15911.pdf",
      "odd href 2": "https://www.nirfindia.org/nirfpdfcdn/2024/graph/Management/IR-M-S-15911.jpg",
      "TLR (100)": "66.29",
      "RPC (100)": "18.15",
      "GO (100)": "83.61",
      "OI (100)": "72.67",
      "PERCEPTION (100)": "15.88",
      "college_city": "Sirmaur",
      "college_state": "Himachal Pradesh",
      "sorting_1": "50.92",
      "college_rank": "57"
    },
    {
      "TLR (100)": "60.10",
      "RPC (100)": "25.90",
      "GO (100)": "81.91",
      "OI (100)": "70.48",
      "PERCEPTION (100)": "15.51",
      "sorting_1": "50.78",
      "college_id": "IR-M-S-156",
      "college_name": "T. A. Pai Management Institute, Manipal",
      "even href": "https://www.nirfindia.org/nirfpdfcdn/2024/pdf/Management/IR-M-S-156.pdf",
      "even href 2": "https://www.nirfindia.org/nirfpdfcdn/2024/graph/Management/IR-M-S-156.jpg",
      "college_city": "Manipal",
      "college_state": "Karnataka",
      "college_rank": "58"
    },
    {
      "college_id": "IR-M-U-0555",
      "college_name": "Graphic Era University",
      "odd href": "https://www.nirfindia.org/nirfpdfcdn/2024/pdf/Management/IR-M-U-0555.pdf",
      "odd href 2": "https://www.nirfindia.org/nirfpdfcdn/2024/graph/Management/IR-M-U-0555.jpg",
      "TLR (100)": "69.16",
      "RPC (100)": "27.41",
      "GO (100)": "59.00",
      "OI (100)": "71.68",
      "PERCEPTION (100)": "26.50",
      "college_city": "Dehradun",
      "college_state": "Uttarakhand",
      "sorting_1": "50.59",
      "college_rank": "59"
    },
    {
      "TLR (100)": "61.48",
      "RPC (100)": "22.09",
      "GO (100)": "69.90",
      "OI (100)": "72.45",
      "PERCEPTION (100)": "42.58",
      "sorting_1": "50.56",
      "college_id": "IR-M-U-0217",
      "college_name": "Christ University",
      "even href": "https://www.nirfindia.org/nirfpdfcdn/2024/pdf/Management/IR-M-U-0217.pdf",
      "even href 2": "https://www.nirfindia.org/nirfpdfcdn/2024/graph/Management/IR-M-U-0217.jpg",
      "college_city": "Bengaluru",
      "college_state": "Karnataka",
      "college_rank": "60"
    },
    {
      "college_id": "IR-M-I-1124",
      "college_name": "International Management Institute, Bhubaneswar",
      "odd href": "https://www.nirfindia.org/nirfpdfcdn/2024/pdf/Management/IR-M-I-1124.pdf",
      "odd href 2": "https://www.nirfindia.org/nirfpdfcdn/2024/graph/Management/IR-M-I-1124.jpg",
      "TLR (100)": "72.06",
      "RPC (100)": "16.72",
      "GO (100)": "78.94",
      "OI (100)": "76.91",
      "PERCEPTION (100)": "2.60",
      "college_city": "Bhubaneswar",
      "college_state": "Odisha",
      "sorting_1": "50.38",
      "college_rank": "61"
    },
    {
      "TLR (100)": "70.66",
      "RPC (100)": "19.77",
      "GO (100)": "69.03",
      "OI (100)": "75.46",
      "PERCEPTION (100)": "12.04",
      "sorting_1": "49.69",
      "college_id": "IR-M-U-0363",
      "college_name": "Siksha `O` Anusandhan",
      "even href": "https://www.nirfindia.org/nirfpdfcdn/2024/pdf/Management/IR-M-U-0363.pdf",
      "even href 2": "https://www.nirfindia.org/nirfpdfcdn/2024/graph/Management/IR-M-U-0363.jpg",
      "college_city": "Bhubaneswar",
      "college_state": "Odisha",
      "college_rank": "62"
    },
    {
      "college_id": "IR-M-C-56616",
      "college_name": "K J Somaiya Institute of Management Studies and Research",
      "odd href": "https://www.nirfindia.org/nirfpdfcdn/2024/pdf/Management/IR-M-C-56616.pdf",
      "odd href 2": "https://www.nirfindia.org/nirfpdfcdn/2024/graph/Management/IR-M-C-56616.jpg",
      "TLR (100)": "68.84",
      "RPC (100)": "23.02",
      "GO (100)": "72.59",
      "OI (100)": "66.72",
      "PERCEPTION (100)": "9.12",
      "college_city": "Mumbai",
      "college_state": "Maharashtra",
      "sorting_1": "49.66",
      "college_rank": "63"
    },
    {
      "TLR (100)": "67.23",
      "RPC (100)": "18.69",
      "GO (100)": "80.54",
      "OI (100)": "65.89",
      "PERCEPTION (100)": "9.55",
      "sorting_1": "49.44",
      "college_id": "IR-M-S-354",
      "college_name": "Birla Institute of Management Technology",
      "even href": "https://www.nirfindia.org/nirfpdfcdn/2024/pdf/Management/IR-M-S-354.pdf",
      "even href 2": "https://www.nirfindia.org/nirfpdfcdn/2024/graph/Management/IR-M-S-354.jpg",
      "college_city": "Greater Noida",
      "college_state": "Uttar Pradesh",
      "college_rank": "64"
    },
    {
      "college_id": "IR-M-U-0099",
      "college_name": "Guru Gobind Singh Indraprastha University",
      "odd href": "https://www.nirfindia.org/nirfpdfcdn/2024/pdf/Management/IR-M-U-0099.pdf",
      "odd href 2": "https://www.nirfindia.org/nirfpdfcdn/2024/graph/Management/IR-M-U-0099.jpg",
      "TLR (100)": "60.92",
      "RPC (100)": "32.16",
      "GO (100)": "73.02",
      "OI (100)": "54.04",
      "PERCEPTION (100)": "14.76",
      "college_city": "New Delhi",
      "college_state": "Delhi",
      "sorting_1": "49.40",
      "college_rank": "65"
    },
    {
      "TLR (100)": "69.63",
      "RPC (100)": "15.81",
      "GO (100)": "72.60",
      "OI (100)": "61.76",
      "PERCEPTION (100)": "29.25",
      "sorting_1": "49.26",
      "college_id": "IR-M-S-331",
      "college_name": "Loyola Institute of Business Administration",
      "even href": "https://www.nirfindia.org/nirfpdfcdn/2024/pdf/Management/IR-M-S-331.pdf",
      "even href 2": "https://www.nirfindia.org/nirfpdfcdn/2024/graph/Management/IR-M-S-331.jpg",
      "college_city": "Chennai",
      "college_state": "Tamil Nadu",
      "college_rank": "66"
    },
    {
      "college_id": "IR-M-U-0356",
      "college_name": "Kalinga Institute of Industrial Technology",
      "odd href": "https://www.nirfindia.org/nirfpdfcdn/2024/pdf/Management/IR-M-U-0356.pdf",
      "odd href 2": "https://www.nirfindia.org/nirfpdfcdn/2024/graph/Management/IR-M-U-0356.jpg",
      "TLR (100)": "79.12",
      "RPC (100)": "22.29",
      "GO (100)": "51.75",
      "OI (100)": "77.22",
      "PERCEPTION (100)": "7.36",
      "college_city": "Bhubaneswar",
      "college_state": "Odisha",
      "sorting_1": "49.24",
      "college_rank": "67"
    },
    {
      "TLR (100)": "48.90",
      "RPC (100)": "57.63",
      "GO (100)": "55.61",
      "OI (100)": "57.51",
      "PERCEPTION (100)": "3.10",
      "sorting_1": "49.14",
      "college_id": "IR-M-U-0410",
      "college_name": "Malaviya National Institute of Technology",
      "even href": "https://www.nirfindia.org/nirfpdfcdn/2024/pdf/Management/IR-M-U-0410.pdf",
      "even href 2": "https://www.nirfindia.org/nirfpdfcdn/2024/graph/Management/IR-M-U-0410.jpg",
      "college_city": "Jaipur",
      "college_state": "Rajasthan",
      "college_rank": "68"
    },
    {
      "college_id": "IR-M-U-0439",
      "college_name": "Anna University",
      "odd href": "https://www.nirfindia.org/nirfpdfcdn/2024/pdf/Management/IR-M-U-0439.pdf",
      "odd href 2": "https://www.nirfindia.org/nirfpdfcdn/2024/graph/Management/IR-M-U-0439.jpg",
      "TLR (100)": "53.37",
      "RPC (100)": "39.59",
      "GO (100)": "63.23",
      "OI (100)": "45.31",
      "PERCEPTION (100)": "38.52",
      "college_city": "Chennai",
      "college_state": "Tamil Nadu",
      "sorting_1": "48.92",
      "college_rank": "69"
    },
    {
      "TLR (100)": "54.24",
      "RPC (100)": "40.29",
      "GO (100)": "68.52",
      "OI (100)": "53.44",
      "PERCEPTION (100)": "12.84",
      "sorting_1": "48.68",
      "college_id": "IR-M-U-0496",
      "college_name": "Aligarh Muslim University",
      "even href": "https://www.nirfindia.org/nirfpdfcdn/2024/pdf/Management/IR-M-U-0496.pdf",
      "even href 2": "https://www.nirfindia.org/nirfpdfcdn/2024/graph/Management/IR-M-U-0496.jpg",
      "college_city": "Aligarh",
      "college_state": "Uttar Pradesh",
      "college_rank": "70"
    },
    {
      "college_id": "IR-M-U-0213",
      "college_name": "Alliance University",
      "odd href": "https://www.nirfindia.org/nirfpdfcdn/2024/pdf/Management/IR-M-U-0213.pdf",
      "odd href 2": "https://www.nirfindia.org/nirfpdfcdn/2024/graph/Management/IR-M-U-0213.jpg",
      "TLR (100)": "78.59",
      "RPC (100)": "9.03",
      "GO (100)": "67.19",
      "OI (100)": "74.92",
      "PERCEPTION (100)": "11.64",
      "college_city": "Bengaluru",
      "college_state": "Karnataka",
      "sorting_1": "48.38",
      "college_rank": "71"
    },
    {
      "TLR (100)": "71.51",
      "RPC (100)": "12.81",
      "GO (100)": "72.36",
      "OI (100)": "60.82",
      "PERCEPTION (100)": "24.76",
      "sorting_1": "48.32",
      "college_id": "IR-M-S-419",
      "college_name": "Jaipuria Institute of Management, Lucknow",
      "even href": "https://www.nirfindia.org/nirfpdfcdn/2024/pdf/Management/IR-M-S-419.pdf",
      "even href 2": "https://www.nirfindia.org/nirfpdfcdn/2024/graph/Management/IR-M-S-419.jpg",
      "college_city": "Lucknow",
      "college_state": "Uttar Pradesh",
      "college_rank": "72"
    },
    {
      "college_id": "IR-M-U-0749",
      "college_name": "Manipal University, Jaipur",
      "odd href": "https://www.nirfindia.org/nirfpdfcdn/2024/pdf/Management/IR-M-U-0749.pdf",
      "odd href 2": "https://www.nirfindia.org/nirfpdfcdn/2024/graph/Management/IR-M-U-0749.jpg",
      "TLR (100)": "66.15",
      "RPC (100)": "24.92",
      "GO (100)": "68.06",
      "OI (100)": "69.07",
      "PERCEPTION (100)": "2.60",
      "college_city": "Jaipur",
      "college_state": "Rajasthan",
      "sorting_1": "48.10",
      "college_rank": "73"
    },
    {
      "TLR (100)": "67.57",
      "RPC (100)": "30.84",
      "GO (100)": "51.62",
      "OI (100)": "77.73",
      "PERCEPTION (100)": "3.10",
      "sorting_1": "47.92",
      "college_id": "IR-M-I-1441",
      "college_name": "Saveetha Institute of Medical and Technical Sciences",
      "even href": "https://www.nirfindia.org/nirfpdfcdn/2024/pdf/Management/IR-M-I-1441.pdf",
      "even href 2": "https://www.nirfindia.org/nirfpdfcdn/2024/graph/Management/IR-M-I-1441.jpg",
      "college_city": "Chennai",
      "college_state": "Tamil Nadu",
      "college_rank": "74"
    },
    {
      "college_id": "IR-M-S-309",
      "college_name": "Jaipuria Institute of Management",
      "odd href": "https://www.nirfindia.org/nirfpdfcdn/2024/pdf/Management/IR-M-S-309.pdf",
      "odd href 2": "https://www.nirfindia.org/nirfpdfcdn/2024/graph/Management/IR-M-S-309.jpg",
      "TLR (100)": "71.33",
      "RPC (100)": "13.88",
      "GO (100)": "74.40",
      "OI (100)": "56.82",
      "PERCEPTION (100)": "14.38",
      "college_city": "Jaipur",
      "college_state": "Rajasthan",
      "sorting_1": "47.56",
      "college_rank": "75"
    },
    {
      "TLR (100)": "67.49",
      "RPC (100)": "24.68",
      "GO (100)": "66.03",
      "OI (100)": "54.08",
      "PERCEPTION (100)": "12.84",
      "sorting_1": "47.55",
      "college_id": "IR-M-U-0263",
      "college_name": "National Institute of Technology Calicut",
      "even href": "https://www.nirfindia.org/nirfpdfcdn/2024/pdf/Management/IR-M-U-0263.pdf",
      "even href 2": "https://www.nirfindia.org/nirfpdfcdn/2024/graph/Management/IR-M-U-0263.jpg",
      "college_city": "Kozhikode",
      "college_state": "Kerala",
      "college_rank": "76"
    },
    {
      "college_id": "IR-M-U-0223",
      "college_name": "Jain University, Bangalore",
      "odd href": "https://www.nirfindia.org/nirfpdfcdn/2024/pdf/Management/IR-M-U-0223.pdf",
      "odd href 2": "https://www.nirfindia.org/nirfpdfcdn/2024/graph/Management/IR-M-U-0223.jpg",
      "TLR (100)": "72.00",
      "RPC (100)": "11.96",
      "GO (100)": "70.81",
      "OI (100)": "68.40",
      "PERCEPTION (100)": "12.84",
      "college_city": "Bengaluru",
      "college_state": "Karnataka",
      "sorting_1": "47.47",
      "college_rank": "77"
    },
    {
      "TLR (100)": "67.80",
      "RPC (100)": "17.57",
      "GO (100)": "70.05",
      "OI (100)": "74.13",
      "PERCEPTION (100)": "3.60",
      "sorting_1": "47.39",
      "college_id": "IR-M-U-0107",
      "college_name": "Jamia Hamdard",
      "even href": "https://www.nirfindia.org/nirfpdfcdn/2024/pdf/Management/IR-M-U-0107.pdf",
      "even href 2": "https://www.nirfindia.org/nirfpdfcdn/2024/graph/Management/IR-M-U-0107.jpg",
      "college_city": "New Delhi",
      "college_state": "Delhi",
      "college_rank": "78"
    },
    {
      "college_id": "IR-M-U-0020",
      "college_name": "Koneru Lakshmaiah Education Foundation University (K L College of Engineering)",
      "odd href": "https://www.nirfindia.org/nirfpdfcdn/2024/pdf/Management/IR-M-U-0020.pdf",
      "odd href 2": "https://www.nirfindia.org/nirfpdfcdn/2024/graph/Management/IR-M-U-0020.jpg",
      "TLR (100)": "70.68",
      "RPC (100)": "26.18",
      "GO (100)": "54.41",
      "OI (100)": "70.35",
      "PERCEPTION (100)": "3.10",
      "college_city": "Vaddeswaram",
      "college_state": "Andhra Pradesh",
      "sorting_1": "47.27",
      "college_rank": "79"
    },
    {
      "TLR (100)": "60.45",
      "RPC (100)": "11.27",
      "GO (100)": "76.60",
      "OI (100)": "57.88",
      "PERCEPTION (100)": "45.02",
      "sorting_1": "47.13",
      "college_id": "IR-M-C-37013",
      "college_name": "PSG College of Technology",
      "even href": "https://www.nirfindia.org/nirfpdfcdn/2024/pdf/Management/IR-M-C-37013.pdf",
      "even href 2": "https://www.nirfindia.org/nirfpdfcdn/2024/graph/Management/IR-M-C-37013.jpg",
      "college_city": "Coimbatore",
      "college_state": "Tamil Nadu",
      "college_rank": "80"
    },
    {
      "college_id": "IR-M-U-0253",
      "college_name": "Cochin University of Science and Technology",
      "odd href": "https://www.nirfindia.org/nirfpdfcdn/2024/pdf/Management/IR-M-U-0253.pdf",
      "odd href 2": "https://www.nirfindia.org/nirfpdfcdn/2024/graph/Management/IR-M-U-0253.jpg",
      "TLR (100)": "70.94",
      "RPC (100)": "19.37",
      "GO (100)": "66.27",
      "OI (100)": "58.71",
      "PERCEPTION (100)": "8.69",
      "college_city": "Cochin",
      "college_state": "Kerala",
      "sorting_1": "47.08",
      "college_rank": "81"
    },
    {
      "TLR (100)": "66.90",
      "RPC (100)": "24.31",
      "GO (100)": "64.38",
      "OI (100)": "47.67",
      "PERCEPTION (100)": "20.06",
      "sorting_1": "47.02",
      "college_id": "IR-M-C-36557",
      "college_name": "Thiagarajar School of Management",
      "even href": "https://www.nirfindia.org/nirfpdfcdn/2024/pdf/Management/IR-M-C-36557.pdf",
      "even href 2": "https://www.nirfindia.org/nirfpdfcdn/2024/graph/Management/IR-M-C-36557.jpg",
      "college_city": "Madurai",
      "college_state": "Tamil Nadu",
      "college_rank": "82"
    },
    {
      "college_id": "IR-M-U-0735",
      "college_name": "BML Munjal University",
      "odd href": "https://www.nirfindia.org/nirfpdfcdn/2024/pdf/Management/IR-M-U-0735.pdf",
      "odd href 2": "https://www.nirfindia.org/nirfpdfcdn/2024/graph/Management/IR-M-U-0735.jpg",
      "TLR (100)": "70.47",
      "RPC (100)": "14.53",
      "GO (100)": "66.98",
      "OI (100)": "74.64",
      "PERCEPTION (100)": "3.10",
      "college_city": "Gurgaon",
      "college_state": "Haryana",
      "sorting_1": "46.67",
      "college_rank": "83"
    },
    {
      "TLR (100)": "67.48",
      "RPC (100)": "10.70",
      "GO (100)": "81.80",
      "OI (100)": "60.71",
      "PERCEPTION (100)": "6.45",
      "sorting_1": "46.53",
      "college_id": "IR-M-S-19472",
      "college_name": "Prin. L.N. Welingkar Institute of Management Development and Research (PGDM)",
      "even href": "https://www.nirfindia.org/nirfpdfcdn/2024/pdf/Management/IR-M-S-19472.pdf",
      "even href 2": "https://www.nirfindia.org/nirfpdfcdn/2024/graph/Management/IR-M-S-19472.jpg",
      "college_city": "Mumbai",
      "college_state": "Maharashtra",
      "college_rank": "84"
    },
    {
      "college_id": "IR-M-U-0267",
      "college_name": "Atal Bihari Vajpayee Indian Institute of Information Technology and Management",
      "odd href": "https://www.nirfindia.org/nirfpdfcdn/2024/pdf/Management/IR-M-U-0267.pdf",
      "odd href 2": "https://www.nirfindia.org/nirfpdfcdn/2024/graph/Management/IR-M-U-0267.jpg",
      "TLR (100)": "62.24",
      "RPC (100)": "23.46",
      "GO (100)": "71.80",
      "OI (100)": "52.78",
      "PERCEPTION (100)": "11.23",
      "college_city": "Gwalior",
      "college_state": "Madhya Pradesh",
      "sorting_1": "46.47",
      "college_rank": "85"
    },
    {
      "TLR (100)": "62.44",
      "RPC (100)": "11.05",
      "GO (100)": "78.23",
      "OI (100)": "82.67",
      "PERCEPTION (100)": "4.57",
      "sorting_1": "46.42",
      "college_id": "IR-M-U-0498",
      "college_name": "Babasaheb Bhimrao Ambedkar University",
      "even href": "https://www.nirfindia.org/nirfpdfcdn/2024/pdf/Management/IR-M-U-0498.pdf",
      "even href 2": "https://www.nirfindia.org/nirfpdfcdn/2024/graph/Management/IR-M-U-0498.jpg",
      "college_city": "Lucknow",
      "college_state": "Uttar Pradesh",
      "college_rank": "86"
    },
    {
      "college_id": "IR-M-S-782",
      "college_name": "Jagan Institute of Management Studies Technical Campus",
      "odd href": "https://www.nirfindia.org/nirfpdfcdn/2024/pdf/Management/IR-M-S-782.pdf",
      "odd href 2": "https://www.nirfindia.org/nirfpdfcdn/2024/graph/Management/IR-M-S-782.jpg",
      "TLR (100)": "66.04",
      "RPC (100)": "8.36",
      "GO (100)": "78.75",
      "OI (100)": "70.66",
      "PERCEPTION (100)": "12.44",
      "college_city": "Delhi",
      "college_state": "Delhi",
      "sorting_1": "46.38",
      "college_rank": "87"
    },
    {
      "TLR (100)": "70.21",
      "RPC (100)": "3.47",
      "GO (100)": "79.10",
      "OI (100)": "72.49",
      "PERCEPTION (100)": "11.23",
      "sorting_1": "46.29",
      "college_id": "IR-M-C-32887",
      "college_name": "New Delhi Institute of Management",
      "even href": "https://www.nirfindia.org/nirfpdfcdn/2024/pdf/Management/IR-M-C-32887.pdf",
      "even href 2": "https://www.nirfindia.org/nirfpdfcdn/2024/graph/Management/IR-M-C-32887.jpg",
      "college_city": "Delhi",
      "college_state": "Delhi",
      "college_rank": "88"
    },
    {
      "college_id": "IR-M-U-0147",
      "college_name": "Pandit Deendayal Energy University",
      "odd href": "https://www.nirfindia.org/nirfpdfcdn/2024/pdf/Management/IR-M-U-0147.pdf",
      "odd href 2": "https://www.nirfindia.org/nirfpdfcdn/2024/graph/Management/IR-M-U-0147.jpg",
      "TLR (100)": "60.14",
      "RPC (100)": "26.68",
      "GO (100)": "75.31",
      "OI (100)": "40.80",
      "PERCEPTION (100)": "2.09",
      "college_city": "Gandhinagar",
      "college_state": "Gujarat",
      "sorting_1": "45.39",
      "college_rank": "89"
    },
    {
      "TLR (100)": "61.75",
      "RPC (100)": "23.08",
      "GO (100)": "64.18",
      "OI (100)": "54.84",
      "PERCEPTION (100)": "12.44",
      "sorting_1": "45.00",
      "college_id": "IR-M-U-0202",
      "college_name": "Birla Institute of Technology",
      "even href": "https://www.nirfindia.org/nirfpdfcdn/2024/pdf/Management/IR-M-U-0202.pdf",
      "even href 2": "https://www.nirfindia.org/nirfpdfcdn/2024/graph/Management/IR-M-U-0202.jpg",
      "college_city": "Ranchi",
      "college_state": "Jharkhand",
      "college_rank": "90"
    },
    {
      "college_id": "IR-M-S-14565",
      "college_name": "National Institute of Bank Management",
      "odd href": "https://www.nirfindia.org/nirfpdfcdn/2024/pdf/Management/IR-M-S-14565.pdf",
      "odd href 2": "https://www.nirfindia.org/nirfpdfcdn/2024/graph/Management/IR-M-S-14565.jpg",
      "TLR (100)": "64.45",
      "RPC (100)": "8.17",
      "GO (100)": "85.01",
      "OI (100)": "58.50",
      "PERCEPTION (100)": "2.09",
      "college_city": "Pune",
      "college_state": "Maharashtra",
      "sorting_1": "44.85",
      "college_rank": "91"
    },
    {
      "TLR (100)": "48.21",
      "RPC (100)": "29.80",
      "GO (100)": "69.61",
      "OI (100)": "55.78",
      "PERCEPTION (100)": "18.02",
      "sorting_1": "44.70",
      "college_id": "IR-M-U-0078",
      "college_name": "Panjab University",
      "even href": "https://www.nirfindia.org/nirfpdfcdn/2024/pdf/Management/IR-M-U-0078.pdf",
      "even href 2": "https://www.nirfindia.org/nirfpdfcdn/2024/graph/Management/IR-M-U-0078.jpg",
      "college_city": "Chandigarh",
      "college_state": "Chandigarh",
      "college_rank": "92"
    },
    {
      "college_id": "IR-M-S-164",
      "college_name": "Rajagiri Business School",
      "odd href": "https://www.nirfindia.org/nirfpdfcdn/2024/pdf/Management/IR-M-S-164.pdf",
      "odd href 2": "https://www.nirfindia.org/nirfpdfcdn/2024/graph/Management/IR-M-S-164.jpg",
      "TLR (100)": "65.55",
      "RPC (100)": "20.92",
      "GO (100)": "59.14",
      "OI (100)": "56.91",
      "PERCEPTION (100)": "8.69",
      "college_city": "Cochin",
      "college_state": "Kerala",
      "sorting_1": "44.33",
      "college_rank": "93"
    },
    {
      "TLR (100)": "63.85",
      "RPC (100)": "0.69",
      "GO (100)": "82.36",
      "OI (100)": "48.63",
      "PERCEPTION (100)": "34.73",
      "sorting_1": "44.17",
      "college_id": "IR-M-N-4",
      "college_name": "Bharathidasan Institute of Management",
      "even href": "https://www.nirfindia.org/nirfpdfcdn/2024/pdf/Management/IR-M-N-4.pdf",
      "even href 2": "https://www.nirfindia.org/nirfpdfcdn/2024/graph/Management/IR-M-N-4.jpg",
      "college_city": "Tiruchirappalli",
      "college_state": "Tamil Nadu",
      "college_rank": "94"
    },
    {
      "college_id": "IR-M-U-0056",
      "college_name": "Tezpur University",
      "odd href": "https://www.nirfindia.org/nirfpdfcdn/2024/pdf/Management/IR-M-U-0056.pdf",
      "odd href 2": "https://www.nirfindia.org/nirfpdfcdn/2024/graph/Management/IR-M-U-0056.jpg",
      "TLR (100)": "63.73",
      "RPC (100)": "16.91",
      "GO (100)": "68.04",
      "OI (100)": "53.22",
      "PERCEPTION (100)": "3.60",
      "college_city": "Tezpur",
      "college_state": "Assam",
      "sorting_1": "43.48",
      "college_rank": "95"
    },
    {
      "TLR (100)": "69.30",
      "RPC (100)": "7.76",
      "GO (100)": "67.84",
      "OI (100)": "60.66",
      "PERCEPTION (100)": "4.09",
      "sorting_1": "43.17",
      "college_id": "IR-M-S-14553",
      "college_name": "National Institute of Agricultural Extension Management",
      "even href": "https://www.nirfindia.org/nirfpdfcdn/2024/pdf/Management/IR-M-S-14553.pdf",
      "even href 2": "https://www.nirfindia.org/nirfpdfcdn/2024/graph/Management/IR-M-S-14553.jpg",
      "college_city": "Hyderabad",
      "college_state": "Telangana",
      "college_rank": "96"
    },
    {
      "college_id": "IR-M-I-1132",
      "college_name": "Institute of Management Technology",
      "odd href": "https://www.nirfindia.org/nirfpdfcdn/2024/pdf/Management/IR-M-I-1132.pdf",
      "odd href 2": "https://www.nirfindia.org/nirfpdfcdn/2024/graph/Management/IR-M-I-1132.jpg",
      "TLR (100)": "55.45",
      "RPC (100)": "13.61",
      "GO (100)": "75.76",
      "OI (100)": "61.83",
      "PERCEPTION (100)": "9.55",
      "college_city": "Hyderabad",
      "college_state": "Telangana",
      "sorting_1": "43.01",
      "college_rank": "97"
    },
    {
      "TLR (100)": "62.42",
      "RPC (100)": "14.99",
      "GO (100)": "64.51",
      "OI (100)": "65.12",
      "PERCEPTION (100)": "2.60",
      "sorting_1": "42.90",
      "college_id": "IR-M-U-0643",
      "college_name": "Galgotias University",
      "even href": "https://www.nirfindia.org/nirfpdfcdn/2024/pdf/Management/IR-M-U-0643.pdf",
      "even href 2": "https://www.nirfindia.org/nirfpdfcdn/2024/graph/Management/IR-M-U-0643.jpg",
      "college_city": "Gautam Budh Nagar",
      "college_state": "Uttar Pradesh",
      "college_rank": "98"
    },
    {
      "college_id": "IR-M-I-1238",
      "college_name": "Krea University",
      "odd href": "https://www.nirfindia.org/nirfpdfcdn/2024/pdf/Management/IR-M-I-1238.pdf",
      "odd href 2": "https://www.nirfindia.org/nirfpdfcdn/2024/graph/Management/IR-M-I-1238.jpg",
      "TLR (100)": "69.73",
      "RPC (100)": "2.22",
      "GO (100)": "64.61",
      "OI (100)": "73.15",
      "PERCEPTION (100)": "9.98",
      "college_city": "Sri City",
      "college_state": "Andhra Pradesh",
      "sorting_1": "42.82",
      "college_rank": "99"
    },
    {
      "TLR (100)": "63.70",
      "RPC (100)": "28.57",
      "GO (100)": "46.53",
      "OI (100)": "46.36",
      "PERCEPTION (100)": "9.98",
      "sorting_1": "42.63",
      "college_id": "IR-M-U-0025",
      "college_name": "National Institute of Technology Warangal",
      "even href": "https://www.nirfindia.org/nirfpdfcdn/2024/pdf/Management/IR-M-U-0025.pdf",
      "even href 2": "https://www.nirfindia.org/nirfpdfcdn/2024/graph/Management/IR-M-U-0025.jpg",
      "college_city": "Warangal",
      "college_state": "Telangana",
      "college_rank": "100"
    }
  ]
}